{"id":"sleepy-lantern-leaf","storyId":"sleepy-lantern-leaf","slug":"sleepy-lantern-leaf","title":"The Sleepy Lantern Leaf","readTime":"8-12 min","ageRange":"1-3 yrs","characterSet":"Meadow Friends","coverThumbRef":"assets/optimized/stories/sleepy-lantern-leaf/p1-thumb.webp","coverOptimizedRef":"assets/optimized/stories/sleepy-lantern-leaf/p1-story.webp","pages":[{"pageId":"p1","order":0,"illustrationAlt":"Text-free illustration for The Sleepy Lantern Leaf, page 1","textPlacement":"right-panel","readAloudText":{"Drift":"A little leaf glows by the path.","Wonder":"A little lantern leaf glows beside the path while the friends get ready for night.","Explore":"A little leaf glowed by the path. Daisy saw it first. Dino bent down slowly. Pip smiled. Itsy whispered, \u201cHello, little light.\u201d"},"optimizedIllustrationRef":"assets/optimized/stories/sleepy-lantern-leaf/p1-story.webp"},{"pageId":"p2","order":1,"illustrationAlt":"Text-free illustration for The Sleepy Lantern Leaf, page 2","textPlacement":"bottom-panel","readAloudText":{"Drift":"The leaf blinks sleepily.","Wonder":"The lantern leaf gives one big sleepy blink, and its glow becomes small.","Explore":"The leaf blinked once. Its light grew tiny. Dino used his quiet voice. \u201cMaybe the leaf is sleepy too.\u201d"},"optimizedIllustrationRef":"assets/optimized/stories/sleepy-lantern-leaf/p2-story.webp"},{"pageId":"p3","order":2,"illustrationAlt":"Text-free illustration for The Sleepy Lantern Leaf, page 3","textPlacement":"top-left","readAloudText":{"Drift":"Daisy wants to help.","Wonder":"Daisy suggests helping the sleepy leaf find a cozy place to rest.","Explore":"Daisy pointed to the soft grass. \u201cWe can help it rest,\u201d she said. Pip nodded. Itsy clapped four soft feet."},"optimizedIllustrationRef":"assets/optimized/stories/sleepy-lantern-leaf/p3-story.webp"},{"pageId":"p4","order":3,"illustrationAlt":"Text-free illustration for The Sleepy Lantern Leaf, page 4","textPlacement":"bottom-panel","readAloudText":{"Drift":"Dino carries the leaf carefully.","Wonder":"Dino carries the lantern leaf carefully on his broad gentle hand.","Explore":"Dino made his hand flat like a bed. The leaf rested there, glowing warm and small."},"optimizedIllustrationRef":"assets/optimized/stories/sleepy-lantern-leaf/p4-story.webp"},{"pageId":"p5","order":4,"illustrationAlt":"Text-free illustration for The Sleepy Lantern Leaf, page 5","textPlacement":"right-panel","readAloudText":{"Drift":"Pip finds a moss pillow.","Wonder":"Pip finds a soft mossy pillow beside a round stone.","Explore":"Pip sniffed the grass and found moss as soft as a yawn. \u201cThis could be a pillow,\u201d he said."},"optimizedIllustrationRef":"assets/optimized/stories/sleepy-lantern-leaf/p5-story.webp"},{"pageId":"p6","order":5,"illustrationAlt":"Text-free illustration for The Sleepy Lantern Leaf, page 6","textPlacement":"bottom-panel","readAloudText":{"Drift":"Itsy moves a twig away.","Wonder":"Itsy gently brushes away a tickly twig so the leaf will not be bothered.","Explore":"A twig leaned too close. Itsy moved it with a tiny bow. \u201cNo tickles at bedtime,\u201d he said."},"optimizedIllustrationRef":"assets/optimized/stories/sleepy-lantern-leaf/p6-story.webp"},{"pageId":"p7","order":6,"illustrationAlt":"Text-free illustration for The Sleepy Lantern Leaf, page 7","textPlacement":"top-left","readAloudText":{"Drift":"Daisy asks the moon for light.","Wonder":"Daisy asks the moon for a small silver blanket of light.","Explore":"Daisy looked up. \u201cMoon, may we borrow a soft blanket?\u201d Moonlight poured down like milk."},"optimizedIllustrationRef":"assets/optimized/stories/sleepy-lantern-leaf/p7-story.webp"},{"pageId":"p8","order":7,"illustrationAlt":"Text-free illustration for The Sleepy Lantern Leaf, page 8","textPlacement":"bottom-panel","readAloudText":{"Drift":"One leaf edge still wiggles.","Wonder":"The leaf rests under moonlight, but one little edge still wiggles awake.","Explore":"The leaf lay on the moss. Most of it was still. One tiny edge went wiggle, wiggle, wiggle."},"optimizedIllustrationRef":"assets/optimized/stories/sleepy-lantern-leaf/p8-story.webp"},{"pageId":"p9","order":8,"illustrationAlt":"Text-free illustration for The Sleepy Lantern Leaf, page 9","textPlacement":"right-panel","readAloudText":{"Drift":"Pip hums a little tune.","Wonder":"Pip hums a tiny tune, and the leaf\u2019s wiggle slows down.","Explore":"Pip hummed hum-hum-hum. The wiggle became slower. Wiggle. Pause. Wiggle."},"optimizedIllustrationRef":"assets/optimized/stories/sleepy-lantern-leaf/p9-story.webp"},{"pageId":"p10","order":9,"illustrationAlt":"Text-free illustration for The Sleepy Lantern Leaf, page 10","textPlacement":"bottom-panel","readAloudText":{"Drift":"Dino breathes warm air.","Wonder":"Dino breathes warm air like a gentle blanket over the leaf.","Explore":"Dino breathed out softly. His warm breath moved over the leaf like a blanket fresh from the sun."},"optimizedIllustrationRef":"assets/optimized/stories/sleepy-lantern-leaf/p10-story.webp"},{"pageId":"p11","order":10,"illustrationAlt":"Text-free illustration for The Sleepy Lantern Leaf, page 11","textPlacement":"top-left","readAloudText":{"Drift":"Itsy counts fireflies.","Wonder":"Itsy counts three fireflies, and the leaf blinks slowly with them.","Explore":"\u201cOne,\u201d said Itsy. A firefly blinked. \u201cTwo.\u201d Another blinked. \u201cThree.\u201d The leaf blinked too."},"optimizedIllustrationRef":"assets/optimized/stories/sleepy-lantern-leaf/p11-story.webp"},{"pageId":"p12","order":11,"illustrationAlt":"Text-free illustration for The Sleepy Lantern Leaf, page 12","textPlacement":"bottom-panel","readAloudText":{"Drift":"Daisy tucks in the moonbeam.","Wonder":"Daisy tucks the moonbeam softly around the leaf\u2019s stem.","Explore":"Daisy tucked the silver light around the leaf\u2019s little stem. \u201cThere,\u201d she whispered. \u201cSnug.\u201d"},"optimizedIllustrationRef":"assets/optimized/stories/sleepy-lantern-leaf/p12-story.webp"},{"pageId":"p13","order":12,"illustrationAlt":"Text-free illustration for The Sleepy Lantern Leaf, page 13","textPlacement":"right-panel","readAloudText":{"Drift":"The leaf glows thank you.","Wonder":"The lantern leaf gives one last golden glow to say thank you.","Explore":"The leaf glowed once, warm and golden. It did not need words. Everyone knew it meant thank you."},"optimizedIllustrationRef":"assets/optimized/stories/sleepy-lantern-leaf/p13-story.webp"},{"pageId":"p14","order":13,"illustrationAlt":"Text-free illustration for The Sleepy Lantern Leaf, page 14","textPlacement":"bottom-panel","readAloudText":{"Drift":"The friends sit quietly.","Wonder":"The friends sit quietly together until the lantern leaf is fully asleep.","Explore":"No one hurried away. Daisy sat. Pip curled close. Dino watched the path. Itsy folded his legs."},"optimizedIllustrationRef":"assets/optimized/stories/sleepy-lantern-leaf/p14-story.webp"},{"pageId":"p15","order":14,"illustrationAlt":"Text-free illustration for The Sleepy Lantern Leaf, page 15","textPlacement":"top-left","readAloudText":{"Drift":"They tiptoe home.","Wonder":"The friends tiptoe home while the tiny leaf sleeps under the moon.","Explore":"The leaf slept under its moon blanket. The friends tiptoed home, slow and soft, with sleepy lights in their eyes."},"optimizedIllustrationRef":"assets/optimized/stories/sleepy-lantern-leaf/p15-story.webp"}]}